qualtrics_utils/__init__.py
qualtrics_utils/codebook/__init__.py
qualtrics_utils/codebook/generate.py
qualtrics_utils/codebook/map_columns.py
qualtrics_utils/misc.py
qualtrics_utils/survey.py
qualtrics_utils/survey_responses_client/__init__.py
qualtrics_utils/survey_responses_client/api/__init__.py
qualtrics_utils/survey_responses_client/api/responses/__init__.py
qualtrics_utils/survey_responses_client/api/responses/create_response.py
qualtrics_utils/survey_responses_client/api/responses/delete_response.py
qualtrics_utils/survey_responses_client/api/responses/delete_uploaded_file.py
qualtrics_utils/survey_responses_client/api/responses/get_response.py
qualtrics_utils/survey_responses_client/api/responses/get_schema.py
qualtrics_utils/survey_responses_client/api/responses/get_uploaded_file.py
qualtrics_utils/survey_responses_client/api/responses/update_response.py
qualtrics_utils/survey_responses_client/client.py
qualtrics_utils/survey_responses_client/errors.py
qualtrics_utils/survey_responses_client/models/__init__.py
qualtrics_utils/survey_responses_client/models/create_response_request.py
qualtrics_utils/survey_responses_client/models/create_response_request_values.py
qualtrics_utils/survey_responses_client/models/create_response_response.py
qualtrics_utils/survey_responses_client/models/create_response_response_result.py
qualtrics_utils/survey_responses_client/models/create_response_with_file_attachments_request.py
qualtrics_utils/survey_responses_client/models/create_response_with_file_attachments_request_file_mapping.py
qualtrics_utils/survey_responses_client/models/default_error_response.py
qualtrics_utils/survey_responses_client/models/delete_response_response.py
qualtrics_utils/survey_responses_client/models/error.py
qualtrics_utils/survey_responses_client/models/get_schema_response.py
qualtrics_utils/survey_responses_client/models/get_schema_response_result.py
qualtrics_utils/survey_responses_client/models/get_schema_response_result_properties.py
qualtrics_utils-1.0.5.dist-info/METADATA
qualtrics_utils-1.0.5.dist-info/WHEEL
qualtrics_utils-1.0.5.dist-info/entry_points.txt
qualtrics_utils-1.0.5.dist-info/RECORD
