Metadata-Version: 2.1
Name: qualtrics-utils
Version: 1.0.5
Summary: Utilities for qualtrics surveys.
Home-page: https://github.com/mkbabb/qualtrics-utils
License: MIT
Keywords: qualtrics,qualtrics-api,qualtrics-util
Author: Mike Babb
Author-email: mike7400@gmail.com
Requires-Python: >=3.12,<4.0
Classifier: License :: OSI Approved :: MIT License
Classifier: Programming Language :: Python :: 3
Classifier: Programming Language :: Python :: 3.12
Requires-Dist: googleapiutils2 (>=0.14,<0.15)
Requires-Dist: loguru (>=0.7.2,<0.8.0)
Requires-Dist: numpy (>=2.1.2,<3.0.0)
Requires-Dist: pandas (>=2.2.3,<3.0.0)
Requires-Dist: requests (>=2.32.3,<3.0.0)
Requires-Dist: sqlalchemy (>=2.0.36,<3.0.0)
Project-URL: Repository, https://github.com/mkbabb/qualtrics-utils
